test_rejey/__init__.py
test_rejey/example.py
test_rejey-0.0.1.dist-info/METADATA
test_rejey-0.0.1.dist-info/WHEEL
test_rejey-0.0.1.dist-info/licenses/LICENSE
test_rejey-0.0.1.dist-info/RECORD
