Metadata-Version: 2.4
Name: test_rejey
Version: 0.0.1
Summary: A easier way to log data to database or files when building applications fast.
Author-email: Rejey Ezekiel Jeyakumar <rehxxz@gmail.com>
License-Expression: MIT
License-File: LICENSE
Classifier: Operating System :: OS Independent
Classifier: Programming Language :: Python :: 3
Requires-Python: >=3.9
